gym_yahtzee/__init__.py
gym_yahtzee/envs/__init__.py
gym_yahtzee/envs/yahtzee_env.py
tests/__init__.py
tests/env_tests.py
gym_yahtzee-1.0.2.dist-info/LICENSE
gym_yahtzee-1.0.2.dist-info/METADATA
gym_yahtzee-1.0.2.dist-info/WHEEL
gym_yahtzee-1.0.2.dist-info/top_level.txt
gym_yahtzee-1.0.2.dist-info/RECORD
