Metadata-Version: 2.1
Name: gym-yahtzee
Version: 1.0.2
Summary: Yahtzee game engine for OpenAI Gym
Home-page: https://github.com/villebro/gym-yahtzee
Author: Ville Brofeldt
Author-email: villebro@apache.org
Maintainer: Ville Brofeldt
Maintainer-email: villebro@apache.org
License: MIT
Platform: UNKNOWN
Classifier: Programming Language :: Python :: 3.6
Classifier: Programming Language :: Python :: 3.7
Classifier: Intended Audience :: Developers
Classifier: License :: OSI Approved :: MIT License
Classifier: Natural Language :: English
Requires-Dist: gym
Requires-Dist: pyhtzee
